{
	"browseMethods": [
	    {
	      	"title": "Browse by Resource Type",
	      	"class":"browse-type-1",
	      	"animateID" : "bt1",
	      	"para": "Looking for a particular resource such as Lesson Plans, or Classroom Activities? Choose this option.",
	      	"imgSrc": "images/browseby-1.svg",
	      	"link": "browse/by-resource"
	    },
	    {
	      	"title": "Browse by Topic",
	      	"class":"browse-type-2",
	      	"animateID" : "bt2",
	      	"para": "Want everything for a particular topic? Choose this option.",
	      	"imgSrc": "images/browseby-2.svg",
	      	"link": "/topic"
	    },
	    {
	      	"title": "Custom search",
	      	"class":"browse-type-3",
	      	"animateID" : "bt3",
	      	"para": "Looking for something specific? Choose this option for advanced filtering options.",
	      	"imgSrc": "images/browseby-3.svg",
	      	"link": "/sign-out"
    	}
    ],
    "updatesList" : [
		{
		  	"title": "Newsela Articles",
		  	"class":"new",
		  	"para": "We’ve added these new things - check them out here!",
		  	"date": "Nov 2016",
		  	"link": "/resource-files/newsela"
		},
		{
			"title": "Classroom Activities",
			"class":"updated",
			"para": "We’ve updated all of this resource to include some new stuff that makes them super relavant to users in 2017. Click here to take another look!",
		  	"date": "Sept 2016",
		  	"link": "/resource-files/classroom-activities"
		}
	]
}